easy_kline/__init__.py
easy_kline/binance.py
easy_kline/bybit.py
easy_kline/check_while_loop.py
easy_kline/datetime_to_timestamp.py
easy_kline/errors.py
easy_kline/exchange.py
easy_kline/get_bar.py
easy_kline/loading_animation.py
easy_kline/oanda.py
easy_kline/response_to_json.py
easy_kline/stream.py
easy_kline/test.py
easy_kline/timeframe_check.py
easy_kline/timeframe_converter.py
easy_kline-0.1.1.dist-info/LICENSE.txt
easy_kline-0.1.1.dist-info/METADATA
easy_kline-0.1.1.dist-info/WHEEL
easy_kline-0.1.1.dist-info/top_level.txt
easy_kline-0.1.1.dist-info/RECORD
